[
{"translatedText": "Фламінга", "detectedSourceLanguage": "en", "input": "Flamingo"},
{"translatedText": "Бекон", "detectedSourceLanguage": "en", "input": "Bacon"},
{"translatedText": "Маршрутка", "detectedSourceLanguage": "en", "input": "Minibus"},
{"translatedText": "Газета", "detectedSourceLanguage": "en", "input": "Newspaper"},
{"translatedText": "Кактус", "detectedSourceLanguage": "en", "input": "Cactus"},
{"translatedText": "Ноч з зоркамі", "detectedSourceLanguage": "en", "input": "Night with stars"},
{"translatedText": "Выдра", "detectedSourceLanguage": "en", "input": "Otter"},
{"translatedText": "Сланечнік", "detectedSourceLanguage": "en", "input": "Sunflower"},
{"translatedText": "Конскі твар", "detectedSourceLanguage": "en", "input": "Horse face"},
{"translatedText": "Круглая шпілька", "detectedSourceLanguage": "en", "input": "Round pushpin"},
{"translatedText": "Партфель", "detectedSourceLanguage": "en", "input": "Briefcase"},
{"translatedText": "Маленькі самалёт", "detectedSourceLanguage": "en", "input": "Small airplane"},
{"translatedText": "Карпавая расцяжка", "detectedSourceLanguage": "en", "input": "Carp streamer"},
{"translatedText": "Красавікі для бегу", "detectedSourceLanguage": "en", "input": "Running shoe"},
{"translatedText": "Спадарожнік", "detectedSourceLanguage": "en", "input": "Satellite"},
{"translatedText": "Міска з лыжкай", "detectedSourceLanguage": "en", "input": "Bowl with spoon"},
{"translatedText": "Лісце лунае на ветры", "detectedSourceLanguage": "en", "input": "Leaf fluttering in wind"},
{"translatedText": "Званочак", "detectedSourceLanguage": "en", "input": "Bellhop bell"},
{"translatedText": "Рулон паперы", "detectedSourceLanguage": "en", "input": "Roll of paper"},
{"translatedText": "Кляновы ліст", "detectedSourceLanguage": "en", "input": "Maple leaf"},
{"translatedText": "Сары", "detectedSourceLanguage": "id", "input": "Sari"},
{"translatedText": "Карта Японіі", "detectedSourceLanguage": "en", "input": "Map of japan"},
{"translatedText": "Лук і стрэлы", "detectedSourceLanguage": "en", "input": "Bow and arrow"},
{"translatedText": "Арангутан", "detectedSourceLanguage": "en", "input": "Orangutan"},
{"translatedText": "Японскія лялькі", "detectedSourceLanguage": "en", "input": "Japanese dolls"},
{"translatedText": "Гаршчок з мёдам", "detectedSourceLanguage": "ro", "input": "Honey pot"},
{"translatedText": "Таксі", "detectedSourceLanguage": "en", "input": "Taxi"},
{"translatedText": "Пляж з парасонам", "detectedSourceLanguage": "en", "input": "Beach with umbrella"},
{"translatedText": "Мікроб", "detectedSourceLanguage": "en", "input": "Microbe"},
{"translatedText": "Тралейбус", "detectedSourceLanguage": "en", "input": "Trolleybus"},
{"translatedText": "Чырвоны канверт", "detectedSourceLanguage": "en", "input": "Red envelope"},
{"translatedText": "Каала", "detectedSourceLanguage": "en", "input": "Koala"},
{"translatedText": "Злая малпа не чуе", "detectedSourceLanguage": "en", "input": "Hear-no-evil monkey"},
{"translatedText": "Свіной нос", "detectedSourceLanguage": "en", "input": "Pig nose"},
{"translatedText": "Папкорн", "detectedSourceLanguage": "en", "input": "Popcorn"},
{"translatedText": "Доўгі барабан", "detectedSourceLanguage": "en", "input": "Long drum"},
{"translatedText": "Разблакіраваны", "detectedSourceLanguage": "en", "input": "Unlocked"},
{"translatedText": "Каціцца па падлозе ад смеху", "detectedSourceLanguage": "en", "input": "Rolling on the floor laughing"},
{"translatedText": "Амары", "detectedSourceLanguage": "en", "input": "Lobster"},
{"translatedText": "Вось", "detectedSourceLanguage": "fr", "input": "Axe"},
{"translatedText": "Разетка", "detectedSourceLanguage": "en", "input": "Rosette"},
{"translatedText": "Кошык", "detectedSourceLanguage": "en", "input": "Basket"},
{"translatedText": "Відэа гульня", "detectedSourceLanguage": "en", "input": "Video game"},
{"translatedText": "Усмешлівы кот з усмешлівымі вачыма", "detectedSourceLanguage": "en", "input": "Grinning cat with smiling eyes"},
{"translatedText": "Чорнае сэрца", "detectedSourceLanguage": "en", "input": "Black heart"},
{"translatedText": "Палачкі для ежы", "detectedSourceLanguage": "en", "input": "Chopsticks"},
{"translatedText": "", "detectedSourceLanguage": "en", "input": ""},
{"translatedText": "Сутыкненне", "detectedSourceLanguage": "en", "input": "Collision"},
{"translatedText": "Аднарог", "detectedSourceLanguage": "en", "input": "Unicorn"},
{"translatedText": "Скрыпка", "detectedSourceLanguage": "en", "input": "Violin"},
{"translatedText": "Пярсцёнак", "detectedSourceLanguage": "en", "input": "Ring"},
{"translatedText": "Лук", "detectedSourceLanguage": "en", "input": "Onion"},
{"translatedText": "Курыца", "detectedSourceLanguage": "en", "input": "Chicken"},
{"translatedText": "09:00", "detectedSourceLanguage": "en", "input": "Nine o’clock"},
{"translatedText": "Одэн", "detectedSourceLanguage": "en", "input": "Oden"},
{"translatedText": "Якар", "detectedSourceLanguage": "en", "input": "Anchor"},
{"translatedText": "Бык", "detectedSourceLanguage": "en", "input": "Ox"},
{"translatedText": "Любоўны гатэль", "detectedSourceLanguage": "en", "input": "Love hotel"},
{"translatedText": "Любоўны ліст", "detectedSourceLanguage": "en", "input": "Love letter"},
{"translatedText": "Брокалі", "detectedSourceLanguage": "en", "input": "Broccoli"},
{"translatedText": "Алень", "detectedSourceLanguage": "en", "input": "Deer"},
{"translatedText": "Васьміног", "detectedSourceLanguage": "en", "input": "Octopus"},
{"translatedText": "Горны", "detectedSourceLanguage": "en", "input": "Mountain"},
{"translatedText": "Дзе гэта", "detectedSourceLanguage": "it", "input": "Dove"},
{"translatedText": "Кухонны нож", "detectedSourceLanguage": "en", "input": "Kitchen knife"},
{"translatedText": "Панда", "detectedSourceLanguage": "en", "input": "Panda"},
{"translatedText": "Павук", "detectedSourceLanguage": "en", "input": "Spider"},
{"translatedText": "Крэсла", "detectedSourceLanguage": "en", "input": "Chair"},
{"translatedText": "Палатка", "detectedSourceLanguage": "en", "input": "Tent"},
{"translatedText": "Клубніцы", "detectedSourceLanguage": "en", "input": "Strawberry"},
{"translatedText": "Усмешлівы твар з усмешлівымі вачыма", "detectedSourceLanguage": "en", "input": "Grinning face with smiling eyes"},
{"translatedText": "Гайка і болт", "detectedSourceLanguage": "en", "input": "Nut and bolt"},
{"translatedText": "Лямпачка", "detectedSourceLanguage": "en", "input": "Light bulb"},
{"translatedText": "Аўтобус", "detectedSourceLanguage": "en", "input": "Bus"},
{"translatedText": "Парасон на зямлі", "detectedSourceLanguage": "en", "input": "Umbrella on ground"},
{"translatedText": "Касцюм сэрца", "detectedSourceLanguage": "en", "input": "Heart suit"},
{"translatedText": "Кіт", "detectedSourceLanguage": "en", "input": "Whale"},
{"translatedText": "Тэлефануйце", "detectedSourceLanguage": "es", "input": "Llama"},
{"translatedText": "Сустрэчнае таксі", "detectedSourceLanguage": "en", "input": "Oncoming taxi"},
{"translatedText": "Канверт", "detectedSourceLanguage": "en", "input": "Envelope"},
{"translatedText": "Кропелька", "detectedSourceLanguage": "en", "input": "Droplet"},
{"translatedText": "Левая бурбалка прамовы", "detectedSourceLanguage": "en", "input": "Left speech bubble"},
{"translatedText": "Валейбол", "detectedSourceLanguage": "en", "input": "Volleyball"},
{"translatedText": "Фантан", "detectedSourceLanguage": "en", "input": "Fountain"},
{"translatedText": "Шар канфеці", "detectedSourceLanguage": "en", "input": "Confetti ball"},
{"translatedText": "Урна з бюлетэнем", "detectedSourceLanguage": "en", "input": "Ballot box with ballot"},
{"translatedText": "Яшчарка", "detectedSourceLanguage": "en", "input": "Lizard"},
{"translatedText": "Першая чвэрць месяца", "detectedSourceLanguage": "en", "input": "First quarter moon"},
{"translatedText": "Брыльянтавы касцюм", "detectedSourceLanguage": "en", "input": "Diamond suit"},
{"translatedText": "Кампутарная мыш", "detectedSourceLanguage": "en", "input": "Computer mouse"},
{"translatedText": "Батанічны твар", "detectedSourceLanguage": "en", "input": "Nerd face"},
{"translatedText": "Маска для дайвінга", "detectedSourceLanguage": "en", "input": "Diving mask"},
{"translatedText": "Маладзік", "detectedSourceLanguage": "en", "input": "New moon"},
{"translatedText": "Грошы з крыламі", "detectedSourceLanguage": "en", "input": "Money with wings"},
{"translatedText": "Трусаў твар", "detectedSourceLanguage": "en", "input": "Rabbit face"},
{"translatedText": "Блакітнае сэрца", "detectedSourceLanguage": "en", "input": "Blue heart"},
{"translatedText": "Каза", "detectedSourceLanguage": "en", "input": "Goat"},
{"translatedText": "Уваходны латок", "detectedSourceLanguage": "en", "input": "Inbox tray"},
{"translatedText": "Чорнае перо", "detectedSourceLanguage": "en", "input": "Black nib"},
{"translatedText": "Свіная морда", "detectedSourceLanguage": "en", "input": "Pig face"},
{"translatedText": "Цыклон", "detectedSourceLanguage": "en", "input": "Cyclone"},
{"translatedText": "Кошык для смецця", "detectedSourceLanguage": "en", "input": "Wastebasket"},
{"translatedText": "Змяншаецца месяц", "detectedSourceLanguage": "en", "input": "Waning gibbous moon"},
{"translatedText": "Аблічча апошняй чвэрці месяца", "detectedSourceLanguage": "en", "input": "Last quarter moon face"},
{"translatedText": "Сава", "detectedSourceLanguage": "en", "input": "Owl"},
{"translatedText": "Кенгуру", "detectedSourceLanguage": "en", "input": "Kangaroo"},
{"translatedText": "Лянота", "detectedSourceLanguage": "en", "input": "Sloth"},
{"translatedText": "Святло паліцэйскай машыны", "detectedSourceLanguage": "en", "input": "Police car light"},
{"translatedText": "Настойлівы твар", "detectedSourceLanguage": "en", "input": "Persevering face"},
{"translatedText": "Чырвоны папяровы ліхтар", "detectedSourceLanguage": "en", "input": "Red paper lantern"},
{"translatedText": "Сучленены грузавік", "detectedSourceLanguage": "en", "input": "Articulated lorry"},
{"translatedText": "Бублік", "detectedSourceLanguage": "en", "input": "Bagel"},
{"translatedText": "Вяселле", "detectedSourceLanguage": "en", "input": "Wedding"},
{"translatedText": "Глобус паказвае Еўропу-Афрыку", "detectedSourceLanguage": "en", "input": "Globe showing europe-africa"},
{"translatedText": "Навушнікі", "detectedSourceLanguage": "en", "input": "Headphone"},
{"translatedText": "Кропля крыві", "detectedSourceLanguage": "en", "input": "Drop of blood"},
{"translatedText": "Падміргвае твар языком", "detectedSourceLanguage": "en", "input": "Winking face with tongue"},
{"translatedText": "Шпілька", "detectedSourceLanguage": "en", "input": "Pushpin"},
{"translatedText": "Пясочны пірог", "detectedSourceLanguage": "en", "input": "Shortcake"},
{"translatedText": "Клубны касцюм", "detectedSourceLanguage": "en", "input": "Club suit"},
{"translatedText": "Грушавая", "detectedSourceLanguage": "en", "input": "Pear"},
{"translatedText": "Смажаны батат", "detectedSourceLanguage": "en", "input": "Roasted sweet potato"},
{"translatedText": "Рэгбі футбол", "detectedSourceLanguage": "en", "input": "Rugby football"},
{"translatedText": "Балансавая шкала", "detectedSourceLanguage": "en", "input": "Balance scale"},
{"translatedText": "Падміргвае твар", "detectedSourceLanguage": "en", "input": "Winking face"},
{"translatedText": "Заплечнік", "detectedSourceLanguage": "en", "input": "Backpack"},
{"translatedText": "Дом з садам", "detectedSourceLanguage": "en", "input": "House with garden"},
{"translatedText": "Гальштук", "detectedSourceLanguage": "en", "input": "Necktie"},
{"translatedText": "Горная чыгунка", "detectedSourceLanguage": "en", "input": "Mountain railway"},
{"translatedText": "Цагляны", "detectedSourceLanguage": "en", "input": "Brick"},
{"translatedText": "Заціск", "detectedSourceLanguage": "en", "input": "Clamp"},
{"translatedText": "Бліны", "detectedSourceLanguage": "en", "input": "Pancakes"},
{"translatedText": "Мяса на косці", "detectedSourceLanguage": "en", "input": "Meat on bone"},
{"translatedText": "Адбіткі лап", "detectedSourceLanguage": "en", "input": "Paw prints"},
{"translatedText": "Акальцаваная планета", "detectedSourceLanguage": "en", "input": "Ringed planet"},
{"translatedText": "Надзьмуты твар", "detectedSourceLanguage": "en", "input": "Pouting face"},
{"translatedText": "Кашалёк", "detectedSourceLanguage": "en", "input": "Purse"},
{"translatedText": "Мурашка", "detectedSourceLanguage": "lt", "input": "Ant"},
{"translatedText": "Грыб", "detectedSourceLanguage": "en", "input": "Mushroom"},
{"translatedText": "Выканальніцкія віды мастацтва", "detectedSourceLanguage": "en", "input": "Performing arts"},
{"translatedText": "Лёд", "detectedSourceLanguage": "en", "input": "Ice"},
{"translatedText": "Закрытая паштовая скрыня з апушчаным сцягам", "detectedSourceLanguage": "en", "input": "Closed mailbox with lowered flag"},
{"translatedText": "Леў", "detectedSourceLanguage": "en", "input": "Lion"},
{"translatedText": "Пэйджэр", "detectedSourceLanguage": "en", "input": "Pager"},
{"translatedText": "Печыва", "detectedSourceLanguage": "pl", "input": "Cookie"},
{"translatedText": "Цюльпан", "detectedSourceLanguage": "en", "input": "Tulip"},
{"translatedText": "Дзевяць трыццаць", "detectedSourceLanguage": "en", "input": "Nine-thirty"},
{"translatedText": "Малаток", "detectedSourceLanguage": "en", "input": "Hammer"},
{"translatedText": "Задуменны твар", "detectedSourceLanguage": "en", "input": "Pensive face"},
{"translatedText": "Цвыркун", "detectedSourceLanguage": "en", "input": "Cricket"},
{"translatedText": "Іскрынкі", "detectedSourceLanguage": "en", "input": "Sparkles"},
{"translatedText": "Стары ключ", "detectedSourceLanguage": "en", "input": "Old key"},
{"translatedText": "Печыва з гаданнем", "detectedSourceLanguage": "en", "input": "Fortune cookie"},
{"translatedText": "Воблака з маланкай і дажджом", "detectedSourceLanguage": "en", "input": "Cloud with lightning and rain"},
{"translatedText": "Форма для баявых мастацтваў", "detectedSourceLanguage": "en", "input": "Martial arts uniform"},
{"translatedText": "Труба", "detectedSourceLanguage": "en", "input": "Trumpet"},
{"translatedText": "Метро", "detectedSourceLanguage": "en", "input": "Metro"},
{"translatedText": "Твар з маноклем", "detectedSourceLanguage": "en", "input": "Face with monocle"},
{"translatedText": "Радыё", "detectedSourceLanguage": "en", "input": "Radio"},
{"translatedText": "Белая кветка", "detectedSourceLanguage": "en", "input": "White flower"},
{"translatedText": "Ззз", "detectedSourceLanguage": "vi", "input": "Zzz"},
{"translatedText": "Картатэка", "detectedSourceLanguage": "en", "input": "Card file box"},
{"translatedText": "Пярэдні птушаня", "detectedSourceLanguage": "en", "input": "Front-facing baby chick"},
{"translatedText": "Расце сэрца", "detectedSourceLanguage": "en", "input": "Growing heart"},
{"translatedText": "Дзесяць гадзін", "detectedSourceLanguage": "en", "input": "Ten o’clock"},
{"translatedText": "Зорка", "detectedSourceLanguage": "en", "input": "Star"},
{"translatedText": "Паветраны шар для думак", "detectedSourceLanguage": "en", "input": "Thought balloon"},
{"translatedText": "Сонца", "detectedSourceLanguage": "en", "input": "Sun"},
{"translatedText": "Глобус паказвае Азія-Аўстралія", "detectedSourceLanguage": "en", "input": "Globe showing asia-australia"},
{"translatedText": "Расада", "detectedSourceLanguage": "en", "input": "Seedling"},
{"translatedText": "Зялёнае яблык", "detectedSourceLanguage": "en", "input": "Green apple"},
{"translatedText": "Востры перац", "detectedSourceLanguage": "en", "input": "Hot pepper"},
{"translatedText": "Збянтэжаны твар", "detectedSourceLanguage": "en", "input": "Confounded face"},
{"translatedText": "Музычныя ноты", "detectedSourceLanguage": "en", "input": "Musical notes"},
{"translatedText": "Вадзяны буйвал", "detectedSourceLanguage": "en", "input": "Water buffalo"},
{"translatedText": "Аладкі", "detectedSourceLanguage": "en", "input": "Flatbread"},
{"translatedText": "Мышка", "detectedSourceLanguage": "en", "input": "Mouse"},
{"translatedText": "Ляжачы твар", "detectedSourceLanguage": "en", "input": "Lying face"},
{"translatedText": "Трохкутная лінейка", "detectedSourceLanguage": "en", "input": "Triangular ruler"},
{"translatedText": "Ваніты асобы", "detectedSourceLanguage": "en", "input": "Face vomiting"},
{"translatedText": "Сіняя кніга", "detectedSourceLanguage": "en", "input": "Blue book"},
{"translatedText": "Твар з павязкай", "detectedSourceLanguage": "en", "input": "Face with head-bandage"},
{"translatedText": "Факс", "detectedSourceLanguage": "en", "input": "Fax machine"},
{"translatedText": "Спагецці", "detectedSourceLanguage": "en", "input": "Spaghetti"},
{"translatedText": "Петарда", "detectedSourceLanguage": "en", "input": "Firecracker"},
{"translatedText": "Чырвонае яблык", "detectedSourceLanguage": "en", "input": "Red apple"},
{"translatedText": "Твар з закачанымі вачыма", "detectedSourceLanguage": "en", "input": "Face with rolling eyes"},
{"translatedText": "Дынамік сярэдняй гучнасці", "detectedSourceLanguage": "en", "input": "Speaker medium volume"},
{"translatedText": "Акумулятар", "detectedSourceLanguage": "en", "input": "Battery"},
{"translatedText": "Дошка для пляскання", "detectedSourceLanguage": "en", "input": "Clapper board"},
{"translatedText": "Дынамік высокай гучнасці", "detectedSourceLanguage": "en", "input": "Speaker high volume"},
{"translatedText": "Плод ківі", "detectedSourceLanguage": "en", "input": "Kiwi fruit"},
{"translatedText": "Білет", "detectedSourceLanguage": "en", "input": "Ticket"},
{"translatedText": "Сырны клін", "detectedSourceLanguage": "en", "input": "Cheese wedge"},
{"translatedText": "Царква", "detectedSourceLanguage": "en", "input": "Church"},
{"translatedText": "Ляціце", "detectedSourceLanguage": "en", "input": "Fly"},
{"translatedText": "Прабірка", "detectedSourceLanguage": "en", "input": "Test tube"},
{"translatedText": "Твар пацалунак", "detectedSourceLanguage": "en", "input": "Face blowing a kiss"},
{"translatedText": "Лісцянае дрэва", "detectedSourceLanguage": "en", "input": "Deciduous tree"},
{"translatedText": "Банкнота фунта", "detectedSourceLanguage": "en", "input": "Pound banknote"},
{"translatedText": "Ўкладкі закладкі", "detectedSourceLanguage": "en", "input": "Bookmark tabs"},
{"translatedText": "Павуцінне", "detectedSourceLanguage": "en", "input": "Spider web"},
{"translatedText": "Адтуліну", "detectedSourceLanguage": "en", "input": "Hole"},
{"translatedText": "Выседжванне птушаня", "detectedSourceLanguage": "en", "input": "Hatching chick"},
{"translatedText": "Мяккае марозіва", "detectedSourceLanguage": "en", "input": "Soft ice cream"},
{"translatedText": "Медаль за 1 месца", "detectedSourceLanguage": "en", "input": "1st place medal"},
{"translatedText": "Чарадзей", "detectedSourceLanguage": "lv", "input": "Ogre"},
{"translatedText": "Відэлец і нож з талеркай", "detectedSourceLanguage": "en", "input": "Fork and knife with plate"},
{"translatedText": "Пакет", "detectedSourceLanguage": "en", "input": "Package"},
{"translatedText": "Стужка-напамін", "detectedSourceLanguage": "en", "input": "Reminder ribbon"},
{"translatedText": "Цылінд", "detectedSourceLanguage": "en", "input": "Top hat"},
{"translatedText": "Адна гадзіна", "detectedSourceLanguage": "en", "input": "One o’clock"},
{"translatedText": "Мячэць", "detectedSourceLanguage": "en", "input": "Mosque"},
{"translatedText": "Узыход сонца над гарамі", "detectedSourceLanguage": "en", "input": "Sunrise over mountains"},
{"translatedText": "Падземны трамвай", "detectedSourceLanguage": "en", "input": "Aerial tramway"},
{"translatedText": "Баклажан", "detectedSourceLanguage": "en", "input": "Eggplant"},
{"translatedText": "Банк", "detectedSourceLanguage": "en", "input": "Bank"},
{"translatedText": "Этыкетка", "detectedSourceLanguage": "en", "input": "Label"},
{"translatedText": "Белы кій", "detectedSourceLanguage": "en", "input": "White cane"},
{"translatedText": "Зашпілька", "detectedSourceLanguage": "en", "input": "Safety pin"},
{"translatedText": "Галавакружэнне", "detectedSourceLanguage": "en", "input": "Dizzy"},
{"translatedText": "Рыбны пірог з закруткай", "detectedSourceLanguage": "en", "input": "Fish cake with swirl"},
{"translatedText": "Пісталет", "detectedSourceLanguage": "en", "input": "Pistol"},
{"translatedText": "Зачынены", "detectedSourceLanguage": "en", "input": "Locked"},
{"translatedText": "Акула", "detectedSourceLanguage": "en", "input": "Shark"},
{"translatedText": "Стомлены твар", "detectedSourceLanguage": "en", "input": "Tired face"},
{"translatedText": "Кекс", "detectedSourceLanguage": "en", "input": "Cupcake"},
{"translatedText": "Будзільнік", "detectedSourceLanguage": "en", "input": "Alarm clock"},
{"translatedText": "Гасцініца", "detectedSourceLanguage": "en", "input": "Hotel"},
{"translatedText": "Лыжка", "detectedSourceLanguage": "en", "input": "Spoon"},
{"translatedText": "Карабель", "detectedSourceLanguage": "en", "input": "Ship"},
{"translatedText": "Свіння", "detectedSourceLanguage": "en", "input": "Pig"},
{"translatedText": "Універмаг", "detectedSourceLanguage": "en", "input": "Department store"},
{"translatedText": "Камера са ўспышкай", "detectedSourceLanguage": "en", "input": "Camera with flash"},
{"translatedText": "Чатыры трыццаць", "detectedSourceLanguage": "en", "input": "Four-thirty"},
{"translatedText": "Тыгр", "detectedSourceLanguage": "en", "input": "Tiger"},
{"translatedText": "Скрынка на вынас", "detectedSourceLanguage": "en", "input": "Takeout box"},
{"translatedText": "Маджонг чырвоны цмок", "detectedSourceLanguage": "en", "input": "Mahjong red dragon"},
{"translatedText": "Глобус паказвае Амерыку", "detectedSourceLanguage": "en", "input": "Globe showing americas"},
{"translatedText": "Ваенны медаль", "detectedSourceLanguage": "en", "input": "Military medal"},
{"translatedText": "Відэакасеты", "detectedSourceLanguage": "it", "input": "Videocassette"},
{"translatedText": "Вылет самалёта", "detectedSourceLanguage": "en", "input": "Airplane departure"},
{"translatedText": "Заклапочаны твар", "detectedSourceLanguage": "en", "input": "Worried face"},
{"translatedText": "Статуя Свабоды", "detectedSourceLanguage": "en", "input": "Statue of liberty"},
{"translatedText": "Ролікавыя канькі", "detectedSourceLanguage": "en", "input": "Roller skate"},
{"translatedText": "Труна", "detectedSourceLanguage": "en", "input": "Coffin"},
{"translatedText": "Тэлефонная трубка", "detectedSourceLanguage": "en", "input": "Telephone receiver"},
{"translatedText": "Скрынка бенто", "detectedSourceLanguage": "en", "input": "Bento box"},
{"translatedText": "Крыштальны шар", "detectedSourceLanguage": "en", "input": "Crystal ball"},
{"translatedText": "Вадзяная хваля", "detectedSourceLanguage": "en", "input": "Water wave"},
{"translatedText": "Прылёт самалёта", "detectedSourceLanguage": "en", "input": "Airplane arrival"},
{"translatedText": "Жаночая шапка", "detectedSourceLanguage": "en", "input": "Woman’s hat"},
{"translatedText": "Смажаныя крэветкі", "detectedSourceLanguage": "en", "input": "Fried shrimp"},
{"translatedText": "Вясёлка", "detectedSourceLanguage": "en", "input": "Rainbow"},
{"translatedText": "Феерверк", "detectedSourceLanguage": "en", "input": "Fireworks"},
{"translatedText": "Каляндар", "detectedSourceLanguage": "en", "input": "Calendar"},
{"translatedText": "Баран", "detectedSourceLanguage": "en", "input": "Ram"},
{"translatedText": "Банан", "detectedSourceLanguage": "en", "input": "Banana"},
{"translatedText": "Памылка", "detectedSourceLanguage": "en", "input": "Bug"},
{"translatedText": "Трапічная рыба", "detectedSourceLanguage": "en", "input": "Tropical fish"},
{"translatedText": "Чэрап", "detectedSourceLanguage": "en", "input": "Skull"},
{"translatedText": "Тэлебачанне", "detectedSourceLanguage": "en", "input": "Television"},
{"translatedText": "Пінгвін", "detectedSourceLanguage": "en", "input": "Penguin"},
{"translatedText": "Ё-йо", "detectedSourceLanguage": "es", "input": "Yo-yo"},
{"translatedText": "Школа", "detectedSourceLanguage": "en", "input": "School"},
{"translatedText": "Сінагога", "detectedSourceLanguage": "en", "input": "Synagogue"},
{"translatedText": "Сшытак з дэкаратыўнай вокладкай", "detectedSourceLanguage": "en", "input": "Notebook with decorative cover"},
{"translatedText": "Аўтарыкша", "detectedSourceLanguage": "el", "input": "Auto rickshaw"},
{"translatedText": "Змяншаецца паўмесяц", "detectedSourceLanguage": "en", "input": "Waning crescent moon"},
{"translatedText": "Пэндзаль", "detectedSourceLanguage": "en", "input": "Paintbrush"},
{"translatedText": "Квітанцыя", "detectedSourceLanguage": "en", "input": "Receipt"},
{"translatedText": "Компас", "detectedSourceLanguage": "en", "input": "Compass"},
{"translatedText": "Секундамер", "detectedSourceLanguage": "en", "input": "Stopwatch"},
{"translatedText": "Аранжавая кніга", "detectedSourceLanguage": "en", "input": "Orange book"},
{"translatedText": "Усмешлівы твар з рагамі", "detectedSourceLanguage": "en", "input": "Smiling face with horns"},
{"translatedText": "Паштовую скрыню", "detectedSourceLanguage": "en", "input": "Postbox"},
{"translatedText": "Уваходныя квіткі", "detectedSourceLanguage": "en", "input": "Admission tickets"},
{"translatedText": "Плачучы твар", "detectedSourceLanguage": "en", "input": "Crying face"},
{"translatedText": "Зачынены ключом", "detectedSourceLanguage": "en", "input": "Locked with key"},
{"translatedText": "Каштанавы", "detectedSourceLanguage": "en", "input": "Chestnut"},
{"translatedText": "Лімон", "detectedSourceLanguage": "en", "input": "Lemon"},
{"translatedText": "Ключ", "detectedSourceLanguage": "en", "input": "Key"},
{"translatedText": "Піца", "detectedSourceLanguage": "en", "input": "Pizza"},
{"translatedText": "Сонны твар", "detectedSourceLanguage": "en", "input": "Sleepy face"},
{"translatedText": "Кашуля для бегу", "detectedSourceLanguage": "en", "input": "Running shirt"},
{"translatedText": "Сумкі для пакупак", "detectedSourceLanguage": "en", "input": "Shopping bags"},
{"translatedText": "Пірог", "detectedSourceLanguage": "lv", "input": "Pie"},
{"translatedText": "Карта свету", "detectedSourceLanguage": "en", "input": "World map"},
{"translatedText": "Багаж", "detectedSourceLanguage": "en", "input": "Luggage"},
{"translatedText": "Сметанковае масла", "detectedSourceLanguage": "en", "input": "Butter"},
{"translatedText": "Матылёк", "detectedSourceLanguage": "en", "input": "Butterfly"},
{"translatedText": "Вараны рыс", "detectedSourceLanguage": "en", "input": "Cooked rice"},
{"translatedText": "Спартыўны ўніверсал", "detectedSourceLanguage": "en", "input": "Sport utility vehicle"},
{"translatedText": "Воблака са снегам", "detectedSourceLanguage": "en", "input": "Cloud with snow"},
{"translatedText": "Стадыён", "detectedSourceLanguage": "en", "input": "Stadium"},
{"translatedText": "Вафлі", "detectedSourceLanguage": "en", "input": "Waffle"},
{"translatedText": "Мастацкая палітра", "detectedSourceLanguage": "en", "input": "Artist palette"},
{"translatedText": "Чатырохлістовая канюшына", "detectedSourceLanguage": "en", "input": "Four leaf clover"},
{"translatedText": "Твар", "detectedSourceLanguage": "en", "input": "Woozy face"},
{"translatedText": "Банкнота ены", "detectedSourceLanguage": "en", "input": "Yen banknote"},
{"translatedText": "Шчыраючы твар", "detectedSourceLanguage": "en", "input": "Shushing face"},
{"translatedText": "Саксафон", "detectedSourceLanguage": "en", "input": "Saxophone"},
{"translatedText": "Твар з парай з носа", "detectedSourceLanguage": "en", "input": "Face with steam from nose"},
{"translatedText": "Паўзунок ўзроўню", "detectedSourceLanguage": "en", "input": "Level slider"},
{"translatedText": "Яйка", "detectedSourceLanguage": "en", "input": "Egg"},
{"translatedText": "Бейсбол", "detectedSourceLanguage": "en", "input": "Baseball"},
{"translatedText": "Гульня памерці", "detectedSourceLanguage": "af", "input": "Game die"},
{"translatedText": "Паліўны помпа", "detectedSourceLanguage": "en", "input": "Fuel pump"},
{"translatedText": "Злы твар з рагамі", "detectedSourceLanguage": "en", "input": "Angry face with horns"},
{"translatedText": "Дынамік нізкай гучнасці", "detectedSourceLanguage": "en", "input": "Speaker low volume"},
{"translatedText": "Горная канатная дарога", "detectedSourceLanguage": "en", "input": "Mountain cableway"},
{"translatedText": "Японская пошта", "detectedSourceLanguage": "en", "input": "Japanese post office"},
{"translatedText": "Паветраны шар", "detectedSourceLanguage": "en", "input": "Balloon"},
{"translatedText": "Пул 8 мяч", "detectedSourceLanguage": "en", "input": "Pool 8 ball"},
{"translatedText": "Месяцовы торт", "detectedSourceLanguage": "en", "input": "Moon cake"},
{"translatedText": "Карусельны конь", "detectedSourceLanguage": "en", "input": "Carousel horse"},
{"translatedText": "Гаечны ключ", "detectedSourceLanguage": "en", "input": "Wrench"},
{"translatedText": "Аплачаная шапка", "detectedSourceLanguage": "en", "input": "Billed cap"},
{"translatedText": "Упрыгожванне сасны", "detectedSourceLanguage": "en", "input": "Pine decoration"},
{"translatedText": "Прыгатаванне ежы", "detectedSourceLanguage": "en", "input": "Cooking"},
{"translatedText": "Чыгуначны шлях", "detectedSourceLanguage": "en", "input": "Railway track"},
{"translatedText": "Кошык", "detectedSourceLanguage": "en", "input": "Shopping cart"},
{"translatedText": "Чатыры гадзіны", "detectedSourceLanguage": "en", "input": "Four o’clock"},
{"translatedText": "Твар з адкрытым ротам", "detectedSourceLanguage": "en", "input": "Face with open mouth"},
{"translatedText": "Заводскі", "detectedSourceLanguage": "en", "input": "Factory"},
{"translatedText": "Кансервы", "detectedSourceLanguage": "en", "input": "Canned food"},
{"translatedText": "Тэлескоп", "detectedSourceLanguage": "en", "input": "Telescope"},
{"translatedText": "Пудзель", "detectedSourceLanguage": "en", "input": "Poodle"},
{"translatedText": "Катэр", "detectedSourceLanguage": "en", "input": "Speedboat"},
{"translatedText": "Свеціцца зорка", "detectedSourceLanguage": "en", "input": "Glowing star"},
{"translatedText": "Бутэлька з ласьёнам", "detectedSourceLanguage": "en", "input": "Lotion bottle"},
{"translatedText": "Скарпіён", "detectedSourceLanguage": "en", "input": "Scorpion"},
{"translatedText": "Аўтамабільны", "detectedSourceLanguage": "en", "input": "Automobile"},
{"translatedText": "Чхаючы твар", "detectedSourceLanguage": "en", "input": "Sneezing face"},
{"translatedText": "Т-рэкс", "detectedSourceLanguage": "en", "input": "T-rex"},
{"translatedText": "Тако", "detectedSourceLanguage": "en", "input": "Taco"},
{"translatedText": "Бенгальскія агні", "detectedSourceLanguage": "en", "input": "Sparkler"},
{"translatedText": "Камень для завіўкі", "detectedSourceLanguage": "en", "input": "Curling stone"},
{"translatedText": "Скрутак", "detectedSourceLanguage": "en", "input": "Scroll"},
{"translatedText": "Медаль за 3 месца", "detectedSourceLanguage": "en", "input": "3rd place medal"},
{"translatedText": "Маркоўны", "detectedSourceLanguage": "en", "input": "Carrot"},
{"translatedText": "Знак пацалунку", "detectedSourceLanguage": "en", "input": "Kiss mark"},
{"translatedText": "07:00", "detectedSourceLanguage": "en", "input": "Seven o’clock"},
{"translatedText": "Будаўніцтва", "detectedSourceLanguage": "en", "input": "Construction"},
{"translatedText": "Нітка", "detectedSourceLanguage": "en", "input": "Thread"},
{"translatedText": "Грошы-рот твар", "detectedSourceLanguage": "en", "input": "Money-mouth face"},
{"translatedText": "Скунс", "detectedSourceLanguage": "en", "input": "Skunk"},
{"translatedText": "Лятаючы дыск", "detectedSourceLanguage": "en", "input": "Flying disc"},
{"translatedText": "Сакэ", "detectedSourceLanguage": "en", "input": "Sake"},
{"translatedText": "Мікрафон", "detectedSourceLanguage": "en", "input": "Microphone"},
{"translatedText": "Пазяхаючы твар", "detectedSourceLanguage": "en", "input": "Yawning face"},
{"translatedText": "Мікраскоп", "detectedSourceLanguage": "en", "input": "Microscope"},
{"translatedText": "Балеткі", "detectedSourceLanguage": "en", "input": "Ballet shoes"},
{"translatedText": "Гарачы напой", "detectedSourceLanguage": "en", "input": "Hot beverage"},
{"translatedText": "Бухгалтэрыя", "detectedSourceLanguage": "en", "input": "Ledger"},
{"translatedText": "Снегавік", "detectedSourceLanguage": "en", "input": "Snowman"},
{"translatedText": "Твар малпы", "detectedSourceLanguage": "en", "input": "Monkey face"},
{"translatedText": "Падагра", "detectedSourceLanguage": "pl", "input": "Dna"},
{"translatedText": "Сшытак", "detectedSourceLanguage": "en", "input": "Notebook"},
{"translatedText": "Вецер твар", "detectedSourceLanguage": "en", "input": "Wind face"},
{"translatedText": "Папугай", "detectedSourceLanguage": "en", "input": "Parrot"},
{"translatedText": "Цырымонія прагляду месяца", "detectedSourceLanguage": "en", "input": "Moon viewing ceremony"},
{"translatedText": "Разгублены твар", "detectedSourceLanguage": "en", "input": "Confused face"},
{"translatedText": "Соль", "detectedSourceLanguage": "en", "input": "Salt"},
{"translatedText": "Фіялетавае сэрца", "detectedSourceLanguage": "en", "input": "Purple heart"},
{"translatedText": "Торт да дня нараджэння", "detectedSourceLanguage": "en", "input": "Birthday cake"},
{"translatedText": "DVD", "detectedSourceLanguage": "en", "input": "Dvd"},
{"translatedText": "Фалафель", "detectedSourceLanguage": "en", "input": "Falafel"},
{"translatedText": "Воўк", "detectedSourceLanguage": "en", "input": "Wolf"},
{"translatedText": "Кампутарны дыск", "detectedSourceLanguage": "en", "input": "Computer disk"},
{"translatedText": "Твар каўбойскага капелюша", "detectedSourceLanguage": "en", "input": "Cowboy hat face"},
{"translatedText": "Спячы твар", "detectedSourceLanguage": "en", "input": "Sleeping face"},
{"translatedText": "Бікіні", "detectedSourceLanguage": "en", "input": "Bikini"},
{"translatedText": "Адкрытая паштовая скрыня з паднятым сцягам", "detectedSourceLanguage": "en", "input": "Open mailbox with raised flag"},
{"translatedText": "Злая малпа", "detectedSourceLanguage": "en", "input": "See-no-evil monkey"},
{"translatedText": "Парасон з кроплямі дажджу", "detectedSourceLanguage": "en", "input": "Umbrella with rain drops"},
{"translatedText": "Усмешлівы твар", "detectedSourceLanguage": "en", "input": "Smirking face"},
{"translatedText": "03:00", "detectedSourceLanguage": "en", "input": "Three o’clock"},
{"translatedText": "Трэкбол", "detectedSourceLanguage": "en", "input": "Trackball"},
{"translatedText": "Калядная ёлка", "detectedSourceLanguage": "en", "input": "Christmas tree"},
{"translatedText": "Агонь", "detectedSourceLanguage": "en", "input": "Fire"},
{"translatedText": "фрыткі", "detectedSourceLanguage": "en", "input": "French fries"},
{"translatedText": "Частка галаваломкі", "detectedSourceLanguage": "en", "input": "Puzzle piece"},
{"translatedText": "Сетка варот", "detectedSourceLanguage": "en", "input": "Goal net"},
{"translatedText": "Пальма", "detectedSourceLanguage": "en", "input": "Palm tree"},
{"translatedText": "Вулкан", "detectedSourceLanguage": "en", "input": "Volcano"},
{"translatedText": "Апошняя чвэрць месяца", "detectedSourceLanguage": "en", "input": "Last quarter moon"},
{"translatedText": "Станцыя", "detectedSourceLanguage": "en", "input": "Station"},
{"translatedText": "Паплечнік", "detectedSourceLanguage": "en", "input": "Mate"},
{"translatedText": "Панэль інструментаў", "detectedSourceLanguage": "en", "input": "Toolbox"},
{"translatedText": "Непацешны твар", "detectedSourceLanguage": "en", "input": "Unamused face"},
{"translatedText": "Дыя лямпа", "detectedSourceLanguage": "hi", "input": "Diya lamp"},
{"translatedText": "Усмешлівы твар з сэрцайкамі", "detectedSourceLanguage": "en", "input": "Smiling face with hearts"},
{"translatedText": "Малітоўныя пацеркі", "detectedSourceLanguage": "en", "input": "Prayer beads"},
{"translatedText": "Тэчка з файламі", "detectedSourceLanguage": "en", "input": "File folder"},
{"translatedText": "Плоскі чаравік", "detectedSourceLanguage": "en", "input": "Flat shoe"},
{"translatedText": "Гістаграма", "detectedSourceLanguage": "en", "input": "Bar chart"},
{"translatedText": "Кракадзіл", "detectedSourceLanguage": "en", "input": "Crocodile"},
{"translatedText": "Узыход сонца", "detectedSourceLanguage": "en", "input": "Sunrise"},
{"translatedText": "Аловак", "detectedSourceLanguage": "fr", "input": "Crayon"},
{"translatedText": "Камізэлька бяспекі", "detectedSourceLanguage": "en", "input": "Safety vest"},
{"translatedText": "Перазвон ветру", "detectedSourceLanguage": "en", "input": "Wind chime"},
{"translatedText": "Маўленчы шар", "detectedSourceLanguage": "en", "input": "Speech balloon"},
{"translatedText": "Завітушкі", "detectedSourceLanguage": "en", "input": "Pretzel"},
{"translatedText": "Усмешлівы кот з вачыма сэрца", "detectedSourceLanguage": "en", "input": "Smiling cat with heart-eyes"},
{"translatedText": "Келіх", "detectedSourceLanguage": "en", "input": "Wine glass"},
{"translatedText": "Відэакамера", "detectedSourceLanguage": "en", "input": "Video camera"},
{"translatedText": "Янот", "detectedSourceLanguage": "en", "input": "Raccoon"},
{"translatedText": "Памідор", "detectedSourceLanguage": "en", "input": "Tomato"},
{"translatedText": "Вожык", "detectedSourceLanguage": "en", "input": "Hedgehog"},
{"translatedText": "Кінжал", "detectedSourceLanguage": "en", "input": "Dagger"},
{"translatedText": "Будаўніцтва", "detectedSourceLanguage": "en", "input": "Building construction"},
{"translatedText": "Кот са слязамі радасці", "detectedSourceLanguage": "en", "input": "Cat with tears of joy"},
{"translatedText": "Леапард", "detectedSourceLanguage": "en", "input": "Leopard"},
{"translatedText": "Безвыразны твар", "detectedSourceLanguage": "en", "input": "Expressionless face"},
{"translatedText": "Адкрыйце тэчку з файламі", "detectedSourceLanguage": "en", "input": "Open file folder"},
{"translatedText": "Цмок", "detectedSourceLanguage": "en", "input": "Dragon"},
{"translatedText": "Сонца з тварам", "detectedSourceLanguage": "en", "input": "Sun with face"},
{"translatedText": "Гульня ў крыкет", "detectedSourceLanguage": "en", "input": "Cricket game"},
{"translatedText": "Музычная партытура", "detectedSourceLanguage": "en", "input": "Musical score"},
{"translatedText": "Аліўкавы", "detectedSourceLanguage": "en", "input": "Olive"},
{"translatedText": "Зялёнае сэрца", "detectedSourceLanguage": "en", "input": "Green heart"},
{"translatedText": "Пяць трыццаць", "detectedSourceLanguage": "en", "input": "Five-thirty"},
{"translatedText": "Зачынены ручкай", "detectedSourceLanguage": "en", "input": "Locked with pen"},
{"translatedText": "Правая бурбалка гневу", "detectedSourceLanguage": "en", "input": "Right anger bubble"},
{"translatedText": "Мужчынскі абутак", "detectedSourceLanguage": "en", "input": "Man’s shoe"},
{"translatedText": "Старонка ўверх", "detectedSourceLanguage": "en", "input": "Page facing up"},
{"translatedText": "Усмешлівы твар", "detectedSourceLanguage": "en", "input": "Grinning face"},
{"translatedText": "Blowfish", "detectedSourceLanguage": "en", "input": "Blowfish"},
{"translatedText": "Сустрэчная паліцэйская машына", "detectedSourceLanguage": "en", "input": "Oncoming police car"},
{"translatedText": "Мяшок грошай", "detectedSourceLanguage": "en", "input": "Money bag"},
{"translatedText": "Ракета", "detectedSourceLanguage": "en", "input": "Rocket"},
{"translatedText": "Сінтаісцкая святыня", "detectedSourceLanguage": "en", "input": "Shinto shrine"},
{"translatedText": "Заснежаная гара", "detectedSourceLanguage": "en", "input": "Snow-capped mountain"},
{"translatedText": "Твар з медыцынскай маскай", "detectedSourceLanguage": "en", "input": "Face with medical mask"},
{"translatedText": "Слімак", "detectedSourceLanguage": "en", "input": "Snail"},
{"translatedText": "Падвесная чыгунка", "detectedSourceLanguage": "en", "input": "Suspension railway"},
{"translatedText": "Скейтборд", "detectedSourceLanguage": "en", "input": "Skateboard"},
{"translatedText": "Трохі нахмураны твар", "detectedSourceLanguage": "en", "input": "Slightly frowning face"},
{"translatedText": "Токійская вежа", "detectedSourceLanguage": "en", "input": "Tokyo tower"},
{"translatedText": "Хамяк", "detectedSourceLanguage": "en", "input": "Hamster"},
{"translatedText": "Адзін трыццаць", "detectedSourceLanguage": "en", "input": "One-thirty"},
{"translatedText": "Выбірайце", "detectedSourceLanguage": "en", "input": "Pick"},
{"translatedText": "Таблетка", "detectedSourceLanguage": "en", "input": "Pill"},
{"translatedText": "Іншапланетны монстар", "detectedSourceLanguage": "en", "input": "Alien monster"},
{"translatedText": "Паром", "detectedSourceLanguage": "en", "input": "Ferry"},
{"translatedText": "Боўлінг", "detectedSourceLanguage": "en", "input": "Bowling"},
{"translatedText": "Какос", "detectedSourceLanguage": "en", "input": "Coconut"},
{"translatedText": "Баскетбол", "detectedSourceLanguage": "en", "input": "Basketball"},
{"translatedText": "Закладка", "detectedSourceLanguage": "en", "input": "Bookmark"},
{"translatedText": "Камета", "detectedSourceLanguage": "en", "input": "Comet"},
{"translatedText": "Алейны барабан", "detectedSourceLanguage": "en", "input": "Oil drum"},
{"translatedText": "Зебра", "detectedSourceLanguage": "en", "input": "Zebra"},
{"translatedText": "Тры трыццаць", "detectedSourceLanguage": "en", "input": "Three-thirty"},
{"translatedText": "Белае сэрца", "detectedSourceLanguage": "en", "input": "White heart"},
{"translatedText": "Пончык", "detectedSourceLanguage": "en", "input": "Doughnut"},
{"translatedText": "Закрытая паштовая скрыня з паднятым сцягам", "detectedSourceLanguage": "en", "input": "Closed mailbox with raised flag"},
{"translatedText": "Пясочныя гадзіны зроблены", "detectedSourceLanguage": "en", "input": "Hourglass done"},
{"translatedText": "05:00", "detectedSourceLanguage": "en", "input": "Five o’clock"},
{"translatedText": "Аўтамагістраль", "detectedSourceLanguage": "en", "input": "Motorway"},
{"translatedText": "Чэрап і скрыжаваныя косткі", "detectedSourceLanguage": "en", "input": "Skull and crossbones"},
{"translatedText": "Чарніцы", "detectedSourceLanguage": "en", "input": "Blueberries"},
{"translatedText": "Аранжавае сэрца", "detectedSourceLanguage": "en", "input": "Orange heart"},
{"translatedText": "Зялёны салата", "detectedSourceLanguage": "en", "input": "Green salad"},
{"translatedText": "Не кажы зла малпа", "detectedSourceLanguage": "en", "input": "Speak-no-evil monkey"},
{"translatedText": "Лёгкая чыгунка", "detectedSourceLanguage": "en", "input": "Light rail"},
{"translatedText": "Хакей на лёдзе", "detectedSourceLanguage": "en", "input": "Ice hockey"},
{"translatedText": "Амфара", "detectedSourceLanguage": "en", "input": "Amphora"},
{"translatedText": "Гара Фудзі", "detectedSourceLanguage": "en", "input": "Mount fuji"},
{"translatedText": "Пахавальная урна", "detectedSourceLanguage": "en", "input": "Funeral urn"},
{"translatedText": "Твар дракона", "detectedSourceLanguage": "en", "input": "Dragon face"},
{"translatedText": "Картатэка", "detectedSourceLanguage": "en", "input": "Card index"},
{"translatedText": "Неглыбокая рондаль з ежай", "detectedSourceLanguage": "en", "input": "Shallow pan of food"},
{"translatedText": "Старонка з завітком", "detectedSourceLanguage": "en", "input": "Page with curl"},
{"translatedText": "Перавернуты твар", "detectedSourceLanguage": "en", "input": "Upside-down face"},
{"translatedText": "Гітара", "detectedSourceLanguage": "en", "input": "Guitar"},
{"translatedText": "Суцэльны купальнік", "detectedSourceLanguage": "en", "input": "One-piece swimsuit"},
{"translatedText": "Сустрэчны аўтамабіль", "detectedSourceLanguage": "en", "input": "Oncoming automobile"},
{"translatedText": "Чырвонае сэрца", "detectedSourceLanguage": "en", "input": "Red heart"},
{"translatedText": "Амерыканскі футбол", "detectedSourceLanguage": "en", "input": "American football"},
{"translatedText": "Туалет", "detectedSourceLanguage": "en", "input": "Toilet"},
{"translatedText": "Цалуючы твар з усмешлівымі вачыма", "detectedSourceLanguage": "en", "input": "Kissing face with smiling eyes"},
{"translatedText": "Нахмураны твар", "detectedSourceLanguage": "en", "input": "Frowning face"},
{"translatedText": "Кот з крывой усмешкай", "detectedSourceLanguage": "en", "input": "Cat with wry smile"},
{"translatedText": "Душ", "detectedSourceLanguage": "en", "input": "Shower"},
{"translatedText": "Клавіятура", "detectedSourceLanguage": "en", "input": "Keyboard"},
{"translatedText": "Мотаскутэр", "detectedSourceLanguage": "da", "input": "Motor scooter"},
{"translatedText": "Злосны твар", "detectedSourceLanguage": "en", "input": "Angry face"},
{"translatedText": "Графік расце разам з іены", "detectedSourceLanguage": "en", "input": "Chart increasing with yen"},
{"translatedText": "Мандарын", "detectedSourceLanguage": "en", "input": "Tangerine"},
{"translatedText": "Перадача", "detectedSourceLanguage": "en", "input": "Gear"},
{"translatedText": "Трава", "detectedSourceLanguage": "en", "input": "Herb"},
{"translatedText": "Трыліснік", "detectedSourceLanguage": "en", "input": "Shamrock"},
{"translatedText": "Аптычны дыск", "detectedSourceLanguage": "en", "input": "Optical disk"},
{"translatedText": "Даляравая банкнота", "detectedSourceLanguage": "en", "input": "Dollar banknote"},
{"translatedText": "Прыцішаны твар", "detectedSourceLanguage": "en", "input": "Hushed face"},
{"translatedText": "Індуісцкі храм", "detectedSourceLanguage": "en", "input": "Hindu temple"},
{"translatedText": "Арол", "detectedSourceLanguage": "en", "input": "Eagle"},
{"translatedText": "Памада", "detectedSourceLanguage": "en", "input": "Lipstick"},
{"translatedText": "Спіральны нататнік", "detectedSourceLanguage": "en", "input": "Spiral notepad"},
{"translatedText": "Сцяг у яме", "detectedSourceLanguage": "en", "input": "Flag in hole"},
{"translatedText": "Прамое трапленне", "detectedSourceLanguage": "en", "input": "Direct hit"},
{"translatedText": "Дыскета", "detectedSourceLanguage": "en", "input": "Floppy disk"},
{"translatedText": "Знак прыпынку", "detectedSourceLanguage": "en", "input": "Stop sign"},
{"translatedText": "Матацыкл", "detectedSourceLanguage": "en", "input": "Motorcycle"},
{"translatedText": "Сумны, але палягчаны твар", "detectedSourceLanguage": "en", "input": "Sad but relieved face"},
{"translatedText": "Занядбаны дом", "detectedSourceLanguage": "en", "input": "Derelict house"},
{"translatedText": "Дрэва Танабата", "detectedSourceLanguage": "ja", "input": "Tanabata tree"},
{"translatedText": "Вустрыца", "detectedSourceLanguage": "en", "input": "Oyster"},
{"translatedText": "Аўтарская ручка", "detectedSourceLanguage": "en", "input": "Fountain pen"},
{"translatedText": "Бутэлька з выскокваючай коркам", "detectedSourceLanguage": "en", "input": "Bottle with popping cork"},
{"translatedText": "Каштоўны камень", "detectedSourceLanguage": "en", "input": "Gem stone"},
{"translatedText": "Дванаццаць трыццаць", "detectedSourceLanguage": "en", "input": "Twelve-thirty"},
{"translatedText": "Млосны твар", "detectedSourceLanguage": "en", "input": "Nauseated face"},
{"translatedText": "Гадзіннік з таймерам", "detectedSourceLanguage": "no", "input": "Timer clock"},
{"translatedText": "Задуманы твар", "detectedSourceLanguage": "en", "input": "Thinking face"},
{"translatedText": "Шэсць трыццаць", "detectedSourceLanguage": "en", "input": "Six-thirty"},
{"translatedText": "Рысавы шарык", "detectedSourceLanguage": "en", "input": "Rice ball"},
{"translatedText": "Самалёт", "detectedSourceLanguage": "en", "input": "Airplane"},
{"translatedText": "Чароўная палачка", "detectedSourceLanguage": "en", "input": "Magic wand"},
{"translatedText": "Чаша для падрыхтоўкі на пару", "detectedSourceLanguage": "en", "input": "Steaming bowl"},
{"translatedText": "Класічны будынак", "detectedSourceLanguage": "en", "input": "Classical building"},
{"translatedText": "Баксёрская пальчатка", "detectedSourceLanguage": "en", "input": "Boxing glove"},
{"translatedText": "Твар без рота", "detectedSourceLanguage": "en", "input": "Face without mouth"},
{"translatedText": "Твар першай чвэрці месяца", "detectedSourceLanguage": "en", "input": "First quarter moon face"},
{"translatedText": "Скрозь", "detectedSourceLanguage": "nl", "input": "Door"},
{"translatedText": "Твар каровы", "detectedSourceLanguage": "en", "input": "Cow face"},
{"translatedText": "Твар з сімваламі на вуснах", "detectedSourceLanguage": "en", "input": "Face with symbols on mouth"},
{"translatedText": "Здзіўлены твар", "detectedSourceLanguage": "en", "input": "Astonished face"},
{"translatedText": "Піньята", "detectedSourceLanguage": "es", "input": "Piñata"},
{"translatedText": "Паруснік", "detectedSourceLanguage": "en", "input": "Sailboat"},
{"translatedText": "Туманны", "detectedSourceLanguage": "en", "input": "Foggy"},
{"translatedText": "Пошта", "detectedSourceLanguage": "en", "input": "Post office"},
{"translatedText": "Трафей", "detectedSourceLanguage": "en", "input": "Trophy"},
{"translatedText": "Відэлец і нож", "detectedSourceLanguage": "en", "input": "Fork and knife"},
{"translatedText": "Гучнагаварыцель", "detectedSourceLanguage": "en", "input": "Loudspeaker"},
{"translatedText": "Пясочныя гадзіны не зроблены", "detectedSourceLanguage": "en", "input": "Hourglass not done"},
{"translatedText": "Катанне на каньках", "detectedSourceLanguage": "en", "input": "Ice skate"},
{"translatedText": "Далей", "detectedSourceLanguage": "bg", "input": "Sled"},
{"translatedText": "Цукеркі", "detectedSourceLanguage": "en", "input": "Candy"},
{"translatedText": "Прыемна", "detectedSourceLanguage": "fy", "input": "Moai"},
{"translatedText": "Каціны твар", "detectedSourceLanguage": "en", "input": "Cat face"},
{"translatedText": "Дом", "detectedSourceLanguage": "en", "input": "House"},
{"translatedText": "Паўлінка", "detectedSourceLanguage": "en", "input": "Peacock"},
{"translatedText": "Умольны твар", "detectedSourceLanguage": "en", "input": "Pleading face"},
{"translatedText": "Двухгорбы вярблюд", "detectedSourceLanguage": "en", "input": "Two-hump camel"},
{"translatedText": "Ўпрыгожванне сэрца", "detectedSourceLanguage": "en", "input": "Heart decoration"},
{"translatedText": "Часнок", "detectedSourceLanguage": "en", "input": "Garlic"},
{"translatedText": "Персікавы", "detectedSourceLanguage": "en", "input": "Peach"},
{"translatedText": "Прынтэр", "detectedSourceLanguage": "en", "input": "Printer"},
{"translatedText": "Шорты", "detectedSourceLanguage": "en", "input": "Shorts"},
{"translatedText": "Вечназялёнае дрэва", "detectedSourceLanguage": "en", "input": "Evergreen tree"},
{"translatedText": "Заварной крэм", "detectedSourceLanguage": "en", "input": "Custard"},
{"translatedText": "Акуляры", "detectedSourceLanguage": "en", "input": "Glasses"},
{"translatedText": "Цыгарэта", "detectedSourceLanguage": "en", "input": "Cigarette"},
{"translatedText": "Вішанькі", "detectedSourceLanguage": "en", "input": "Cherries"},
{"translatedText": "Сонца за невялікай хмаркай", "detectedSourceLanguage": "en", "input": "Sun behind small cloud"},
{"translatedText": "Ланцужкі", "detectedSourceLanguage": "en", "input": "Chains"},
{"translatedText": "Стомлены твар", "detectedSourceLanguage": "en", "input": "Weary face"},
{"translatedText": "Прывід", "detectedSourceLanguage": "en", "input": "Ghost"},
{"translatedText": "Губка", "detectedSourceLanguage": "en", "input": "Sponge"},
{"translatedText": "Снегавік без снегу", "detectedSourceLanguage": "en", "input": "Snowman without snow"},
{"translatedText": "Гарадскі пейзаж", "detectedSourceLanguage": "en", "input": "Cityscape"},
{"translatedText": "Крэветкі", "detectedSourceLanguage": "en", "input": "Shrimp"},
{"translatedText": "Спартыўны медаль", "detectedSourceLanguage": "en", "input": "Sports medal"},
{"translatedText": "Стакан шклянкі", "detectedSourceLanguage": "en", "input": "Tumbler glass"},
{"translatedText": "Сонца за воблакам", "detectedSourceLanguage": "en", "input": "Sun behind cloud"},
{"translatedText": "Фаршаваныя аладкі", "detectedSourceLanguage": "en", "input": "Stuffed flatbread"},
{"translatedText": "Забіваць і абіраць", "detectedSourceLanguage": "en", "input": "Hammer and pick"},
{"translatedText": "Цалуючы твар", "detectedSourceLanguage": "en", "input": "Kissing face"},
{"translatedText": "Гарыла", "detectedSourceLanguage": "en", "input": "Gorilla"},
{"translatedText": "Вудка", "detectedSourceLanguage": "en", "input": "Fishing pole"},
{"translatedText": "Электрычная вілка", "detectedSourceLanguage": "en", "input": "Electric plug"},
{"translatedText": "Жыраф", "detectedSourceLanguage": "en", "input": "Giraffe"},
{"translatedText": "Раздзяляльнікі картатэкі", "detectedSourceLanguage": "en", "input": "Card index dividers"},
{"translatedText": "Замаскіраваны твар", "detectedSourceLanguage": "en", "input": "Disguised face"},
{"translatedText": "Поўны месяц", "detectedSourceLanguage": "en", "input": "Full moon"},
{"translatedText": "Электронная пошта", "detectedSourceLanguage": "it", "input": "E-mail"},
{"translatedText": "Скрэпка", "detectedSourceLanguage": "en", "input": "Paperclip"},
{"translatedText": "Зубная шчотка", "detectedSourceLanguage": "en", "input": "Toothbrush"},
{"translatedText": "Паліцэйская машына", "detectedSourceLanguage": "en", "input": "Police car"},
{"translatedText": "Усмешлівы твар са слязамі", "detectedSourceLanguage": "en", "input": "Smiling face with tear"},
{"translatedText": "Сноп рысу", "detectedSourceLanguage": "en", "input": "Sheaf of rice"},
{"translatedText": "Лядзяш", "detectedSourceLanguage": "en", "input": "Lollipop"},
{"translatedText": "Чарвяк", "detectedSourceLanguage": "en", "input": "Worm"},
{"translatedText": "Кааба", "detectedSourceLanguage": "bn", "input": "Kaaba"},
{"translatedText": "Рамкі для фільмаў", "detectedSourceLanguage": "en", "input": "Film frames"},
{"translatedText": "Жаба", "detectedSourceLanguage": "en", "input": "Frog"},
{"translatedText": "Пальчаткі", "detectedSourceLanguage": "en", "input": "Gloves"},
{"translatedText": "Магніт", "detectedSourceLanguage": "en", "input": "Magnet"},
{"translatedText": "Знічка", "detectedSourceLanguage": "en", "input": "Shooting star"},
{"translatedText": "Надзьмуты кот", "detectedSourceLanguage": "en", "input": "Pouting cat"},
{"translatedText": "Крэдытная картка", "detectedSourceLanguage": "en", "input": "Credit card"},
{"translatedText": "Музычная нота", "detectedSourceLanguage": "en", "input": "Musical note"},
{"translatedText": "Кнігі", "detectedSourceLanguage": "en", "input": "Books"},
{"translatedText": "Вертыкальны святлафор", "detectedSourceLanguage": "en", "input": "Vertical traffic light"},
{"translatedText": "Сядзенне", "detectedSourceLanguage": "en", "input": "Seat"},
{"translatedText": "Дыяграма павялічваецца", "detectedSourceLanguage": "en", "input": "Chart increasing"},
{"translatedText": "Певень", "detectedSourceLanguage": "en", "input": "Rooster"},
{"translatedText": "Твар маладзіка", "detectedSourceLanguage": "en", "input": "New moon face"},
{"translatedText": "Сем трыццаць", "detectedSourceLanguage": "en", "input": "Seven-thirty"},
{"translatedText": "Марозіва", "detectedSourceLanguage": "en", "input": "Ice cream"},
{"translatedText": "Лісіца", "detectedSourceLanguage": "en", "input": "Fox"},
{"translatedText": "Софтбол", "detectedSourceLanguage": "en", "input": "Softball"},
{"translatedText": "Шакаладная плітка", "detectedSourceLanguage": "en", "input": "Chocolate bar"},
{"translatedText": "Ручкі кіравання", "detectedSourceLanguage": "en", "input": "Control knobs"},
{"translatedText": "Дама жук", "detectedSourceLanguage": "en", "input": "Lady beetle"},
{"translatedText": "Твар ухмыляўся ад поту", "detectedSourceLanguage": "en", "input": "Grinning face with sweat"},
{"translatedText": "Ружа", "detectedSourceLanguage": "en", "input": "Rose"},
{"translatedText": "Твар крычыць ад страху", "detectedSourceLanguage": "en", "input": "Face screaming in fear"},
{"translatedText": "Звякаюць шклянкі", "detectedSourceLanguage": "en", "input": "Clinking glasses"},
{"translatedText": "Б&#39;ецца сэрца", "detectedSourceLanguage": "en", "input": "Beating heart"},
{"translatedText": "Алембічны", "detectedSourceLanguage": "en", "input": "Alembic"},
{"translatedText": "Стужка", "detectedSourceLanguage": "en", "input": "Ribbon"},
{"translatedText": "Выбухае галава", "detectedSourceLanguage": "en", "input": "Exploding head"},
{"translatedText": "Кветкавыя ігральныя карты", "detectedSourceLanguage": "en", "input": "Flower playing cards"},
{"translatedText": "Абутак на высокім абцасе", "detectedSourceLanguage": "en", "input": "High-heeled shoe"},
{"translatedText": "Джойсцік", "detectedSourceLanguage": "en", "input": "Joystick"},
{"translatedText": "Ухмыляючыся прыжмураны твар", "detectedSourceLanguage": "en", "input": "Grinning squinting face"},
{"translatedText": "Аўтобусны прыпынак", "detectedSourceLanguage": "en", "input": "Bus stop"},
{"translatedText": "Буфер абмену", "detectedSourceLanguage": "en", "input": "Clipboard"},
{"translatedText": "Жахлівы твар", "detectedSourceLanguage": "en", "input": "Zany face"},
{"translatedText": "Хмара з дажджом", "detectedSourceLanguage": "en", "input": "Cloud with rain"},
{"translatedText": "Пчала", "detectedSourceLanguage": "en", "input": "Honeybee"},
{"translatedText": "Качка", "detectedSourceLanguage": "en", "input": "Duck"},
{"translatedText": "Шпрыц", "detectedSourceLanguage": "en", "input": "Syringe"},
{"translatedText": "Цягнік", "detectedSourceLanguage": "en", "input": "Train"},
{"translatedText": "Боцік жаночы", "detectedSourceLanguage": "en", "input": "Woman’s boot"},
{"translatedText": "Канапа і лямпа", "detectedSourceLanguage": "en", "input": "Couch and lamp"},
{"translatedText": "Адзінаццаць трыццаць", "detectedSourceLanguage": "en", "input": "Eleven-thirty"},
{"translatedText": "Клейкая павязка", "detectedSourceLanguage": "en", "input": "Adhesive bandage"},
{"translatedText": "Адрыўны каляндар", "detectedSourceLanguage": "en", "input": "Tear-off calendar"},
{"translatedText": "паўмесяц", "detectedSourceLanguage": "en", "input": "Crescent moon"},
{"translatedText": "Ручная інвалідная каляска", "detectedSourceLanguage": "en", "input": "Manual wheelchair"},
{"translatedText": "Хот-дог", "detectedSourceLanguage": "en", "input": "Hot dog"},
{"translatedText": "Гарачы твар", "detectedSourceLanguage": "en", "input": "Hot face"},
{"translatedText": "Сумка-клатч", "detectedSourceLanguage": "en", "input": "Clutch bag"},
{"translatedText": "Авакада", "detectedSourceLanguage": "en", "input": "Avocado"},
{"translatedText": "Настольны кампутар", "detectedSourceLanguage": "en", "input": "Desktop computer"},
{"translatedText": "Жаночыя сандалі", "detectedSourceLanguage": "en", "input": "Woman’s sandal"},
{"translatedText": "Бадмінтон", "detectedSourceLanguage": "en", "input": "Badminton"},
{"translatedText": "Мабільны тэлефон са стрэлкай", "detectedSourceLanguage": "en", "input": "Mobile phone with arrow"},
{"translatedText": "Птушыная ножка", "detectedSourceLanguage": "en", "input": "Poultry leg"},
{"translatedText": "Манарэйка", "detectedSourceLanguage": "en", "input": "Monorail"},
{"translatedText": "Акуляры", "detectedSourceLanguage": "en", "input": "Goggles"},
{"translatedText": "Абдымае твар", "detectedSourceLanguage": "en", "input": "Hugging face"},
{"translatedText": "Зоркі", "detectedSourceLanguage": "en", "input": "Star-struck"},
{"translatedText": "Змяя", "detectedSourceLanguage": "en", "input": "Snake"},
{"translatedText": "Кулявой цягнік", "detectedSourceLanguage": "en", "input": "Bullet train"},
{"translatedText": "Малпа", "detectedSourceLanguage": "en", "input": "Monkey"},
{"translatedText": "Малаток і гаечны ключ", "detectedSourceLanguage": "en", "input": "Hammer and wrench"},
{"translatedText": "Белы мядзведзь", "detectedSourceLanguage": "en", "input": "Polar bear"},
{"translatedText": "Хлеб", "detectedSourceLanguage": "en", "input": "Bread"},
{"translatedText": "Маланка-рот твар", "detectedSourceLanguage": "en", "input": "Zipper-mouth face"},
{"translatedText": "Шклянка малака", "detectedSourceLanguage": "en", "input": "Glass of milk"},
{"translatedText": "Трусы", "detectedSourceLanguage": "en", "input": "Briefs"},
{"translatedText": "Жоўтае сэрца", "detectedSourceLanguage": "en", "input": "Yellow heart"},
{"translatedText": "Манга", "detectedSourceLanguage": "en", "input": "Mango"},
{"translatedText": "Прыглушаны дынамік", "detectedSourceLanguage": "en", "input": "Muted speaker"},
{"translatedText": "Лебедзь", "detectedSourceLanguage": "en", "input": "Swan"},
{"translatedText": "Букет", "detectedSourceLanguage": "en", "input": "Bouquet"},
{"translatedText": "Рыба", "detectedSourceLanguage": "en", "input": "Fish"},
{"translatedText": "Спіральны каляндар", "detectedSourceLanguage": "en", "input": "Spiral calendar"},
{"translatedText": "Камера", "detectedSourceLanguage": "en", "input": "Camera"},
{"translatedText": "Піўная кружка", "detectedSourceLanguage": "en", "input": "Beer mug"},
{"translatedText": "Усмешлівы кот", "detectedSourceLanguage": "en", "input": "Grinning cat"},
{"translatedText": "Пасажырскае судна", "detectedSourceLanguage": "en", "input": "Passenger ship"},
{"translatedText": "Дыня", "detectedSourceLanguage": "en", "input": "Melon"},
{"translatedText": "Брытва", "detectedSourceLanguage": "en", "input": "Razor"},
{"translatedText": "Трохі ўсмешлівы твар", "detectedSourceLanguage": "en", "input": "Slightly smiling face"},
{"translatedText": "Вока ў бурбалцы прамовы", "detectedSourceLanguage": "en", "input": "Eye in speech bubble"},
{"translatedText": "Грымасны твар", "detectedSourceLanguage": "en", "input": "Grimacing face"},
{"translatedText": "Калас", "detectedSourceLanguage": "en", "input": "Ear of corn"},
{"translatedText": "Бутэрброд", "detectedSourceLanguage": "en", "input": "Sandwich"},
{"translatedText": "Завяла кветка", "detectedSourceLanguage": "en", "input": "Wilted flower"},
{"translatedText": "Нарэзка мяса", "detectedSourceLanguage": "en", "input": "Cut of meat"},
{"translatedText": "Закрытая кніга", "detectedSourceLanguage": "en", "input": "Closed book"},
{"translatedText": "Абак", "detectedSourceLanguage": "en", "input": "Abacus"},
{"translatedText": "Вогнетушыцель", "detectedSourceLanguage": "en", "input": "Fire extinguisher"},
{"translatedText": "Плунжер", "detectedSourceLanguage": "en", "input": "Plunger"},
{"translatedText": "Камінны гадзіннік", "detectedSourceLanguage": "en", "input": "Mantelpiece clock"},
{"translatedText": "Расчараваны твар", "detectedSourceLanguage": "en", "input": "Disappointed face"},
{"translatedText": "Грузавік для дастаўкі", "detectedSourceLanguage": "en", "input": "Delivery truck"},
{"translatedText": "Котка плача", "detectedSourceLanguage": "en", "input": "Crying cat"},
{"translatedText": "Гарызантальны святлафор", "detectedSourceLanguage": "en", "input": "Horizontal traffic light"},
{"translatedText": "Прыжмураны твар языком", "detectedSourceLanguage": "en", "input": "Squinting face with tongue"},
{"translatedText": "Сняжынка", "detectedSourceLanguage": "en", "input": "Snowflake"},
{"translatedText": "Сонцаахоўныя акуляры", "detectedSourceLanguage": "en", "input": "Sunglasses"},
{"translatedText": "Тамале", "detectedSourceLanguage": "en", "input": "Tamale"},
{"translatedText": "Усмешлівы твар з вачыма сэрца", "detectedSourceLanguage": "en", "input": "Smiling face with heart-eyes"},
{"translatedText": "Пустыня", "detectedSourceLanguage": "en", "input": "Desert"},
{"translatedText": "Два трыццаць", "detectedSourceLanguage": "en", "input": "Two-thirty"},
{"translatedText": "Нажніцы", "detectedSourceLanguage": "en", "input": "Scissors"},
{"translatedText": "гамбургер", "detectedSourceLanguage": "de", "input": "Hamburger"},
{"translatedText": "Вясёлы твар", "detectedSourceLanguage": "en", "input": "Partying face"},
{"translatedText": "Нейтральны твар", "detectedSourceLanguage": "en", "input": "Neutral face"},
{"translatedText": "Усмешлівы твар з усмешлівымі вачыма", "detectedSourceLanguage": "en", "input": "Smiling face with smiling eyes"},
{"translatedText": "Трывожны твар з потам", "detectedSourceLanguage": "en", "input": "Anxious face with sweat"},
{"translatedText": "Іншапланецянін", "detectedSourceLanguage": "en", "input": "Alien"},
{"translatedText": "Пацук", "detectedSourceLanguage": "en", "input": "Rat"},
{"translatedText": "Звон з касой рысай", "detectedSourceLanguage": "en", "input": "Bell with slash"},
{"translatedText": "Усмешлівы твар у сонцаахоўных акулярах", "detectedSourceLanguage": "en", "input": "Smiling face with sunglasses"},
{"translatedText": "Усмешлівы твар з вялікімі вачыма", "detectedSourceLanguage": "en", "input": "Grinning face with big eyes"},
{"translatedText": "Насарог", "detectedSourceLanguage": "en", "input": "Rhinoceros"},
{"translatedText": "Памятка", "detectedSourceLanguage": "en", "input": "Memo"},
{"translatedText": "Паліто", "detectedSourceLanguage": "en", "input": "Coat"},
{"translatedText": "Кіт, які брыдзе", "detectedSourceLanguage": "en", "input": "Spouting whale"},
{"translatedText": "Дамы", "detectedSourceLanguage": "en", "input": "Houses"},
{"translatedText": "Лятаючая талерка", "detectedSourceLanguage": "en", "input": "Flying saucer"},
{"translatedText": "Футболка", "detectedSourceLanguage": "en", "input": "T-shirt"},
{"translatedText": "Чашка без ручкі", "detectedSourceLanguage": "en", "input": "Teacup without handle"},
{"translatedText": "Камар", "detectedSourceLanguage": "en", "input": "Mosquito"},
{"translatedText": "Вішнёвы колер", "detectedSourceLanguage": "en", "input": "Cherry blossom"},
{"translatedText": "Кактэйльная чарка", "detectedSourceLanguage": "en", "input": "Cocktail glass"},
{"translatedText": "Ноўтбук", "detectedSourceLanguage": "en", "input": "Laptop"},
{"translatedText": "Карона", "detectedSourceLanguage": "en", "input": "Crown"},
{"translatedText": "Бегемот", "detectedSourceLanguage": "en", "input": "Hippopotamus"},
{"translatedText": "Асенні ліст", "detectedSourceLanguage": "de", "input": "Fallen leaf"},
{"translatedText": "Агурок", "detectedSourceLanguage": "en", "input": "Cucumber"},
{"translatedText": "Твар з тэрмометрам", "detectedSourceLanguage": "en", "input": "Face with thermometer"},
{"translatedText": "Барсук", "detectedSourceLanguage": "en", "input": "Badger"},
{"translatedText": "Стетоскоп", "detectedSourceLanguage": "en", "input": "Stethoscope"},
{"translatedText": "Гоблін", "detectedSourceLanguage": "en", "input": "Goblin"},
{"translatedText": "Тэлефон", "detectedSourceLanguage": "en", "input": "Telephone"},
{"translatedText": "Конь", "detectedSourceLanguage": "en", "input": "Horse"},
{"translatedText": "Спасылка", "detectedSourceLanguage": "en", "input": "Link"},
{"translatedText": "Данга", "detectedSourceLanguage": "ja", "input": "Dango"},
{"translatedText": "Выпускная шапка", "detectedSourceLanguage": "en", "input": "Graduation cap"},
{"translatedText": "Багетны хлеб", "detectedSourceLanguage": "en", "input": "Baguette bread"},
{"translatedText": "Павялічальнае шкло нахілена налева", "detectedSourceLanguage": "en", "input": "Magnifying glass tilted left"},
{"translatedText": "Сабака-павадыр", "detectedSourceLanguage": "en", "input": "Guide dog"},
{"translatedText": "Банджа", "detectedSourceLanguage": "en", "input": "Banjo"},
{"translatedText": "Гаршчок з ежай", "detectedSourceLanguage": "en", "input": "Pot of food"},
{"translatedText": "Лакаматыў", "detectedSourceLanguage": "en", "input": "Locomotive"},
{"translatedText": "Дыяграма памяншаецца", "detectedSourceLanguage": "en", "input": "Chart decreasing"},
{"translatedText": "Сукенка", "detectedSourceLanguage": "en", "input": "Dress"},
{"translatedText": "Сонца за дажджавой хмарай", "detectedSourceLanguage": "en", "input": "Sun behind rain cloud"},
{"translatedText": "Студыйны мікрафон", "detectedSourceLanguage": "en", "input": "Studio microphone"},
{"translatedText": "Джокер", "detectedSourceLanguage": "en", "input": "Joker"},
{"translatedText": "Нахмураны твар з адкрытым ротам", "detectedSourceLanguage": "en", "input": "Frowning face with open mouth"},
{"translatedText": "Адкрыць паштовую скрыню з апушчаным сцягам", "detectedSourceLanguage": "en", "input": "Open mailbox with lowered flag"},
{"translatedText": "Стомлены кот", "detectedSourceLanguage": "en", "input": "Weary cat"},
{"translatedText": "Усмешлівы твар з німбам", "detectedSourceLanguage": "en", "input": "Smiling face with halo"},
{"translatedText": "Апушчаны твар ад поту", "detectedSourceLanguage": "en", "input": "Downcast face with sweat"},
{"translatedText": "Амерыканскія горкі", "detectedSourceLanguage": "en", "input": "Roller coaster"},
{"translatedText": "Скрыжаваныя мячы", "detectedSourceLanguage": "en", "input": "Crossed swords"},
{"translatedText": "Паходны чаравік", "detectedSourceLanguage": "en", "input": "Hiking boot"},
{"translatedText": "Партыйны поппер", "detectedSourceLanguage": "en", "input": "Party popper"},
{"translatedText": "Карціна ў рамцы", "detectedSourceLanguage": "en", "input": "Framed picture"},
{"translatedText": "Дэльфін", "detectedSourceLanguage": "en", "input": "Dolphin"},
{"translatedText": "Верталёт", "detectedSourceLanguage": "en", "input": "Helicopter"},
{"translatedText": "Восем трыццаць", "detectedSourceLanguage": "en", "input": "Eight-thirty"},
{"translatedText": "Барабан", "detectedSourceLanguage": "en", "input": "Drum"},
{"translatedText": "Лыжы", "detectedSourceLanguage": "en", "input": "Skis"},
{"translatedText": "Кропелькі поту", "detectedSourceLanguage": "en", "input": "Sweat droplets"},
{"translatedText": "Птушка", "detectedSourceLanguage": "en", "input": "Bird"},
{"translatedText": "Разбітае сэрца", "detectedSourceLanguage": "en", "input": "Broken heart"},
{"translatedText": "Заўрапод", "detectedSourceLanguage": "en", "input": "Sauropod"},
{"translatedText": "Заход сонца", "detectedSourceLanguage": "en", "input": "Sunset"},
{"translatedText": "Канверт са стрэлкай", "detectedSourceLanguage": "en", "input": "Envelope with arrow"},
{"translatedText": "Мышыны твар", "detectedSourceLanguage": "en", "input": "Mouse face"},
{"translatedText": "Два сэрца", "detectedSourceLanguage": "en", "input": "Two hearts"},
{"translatedText": "Дзіцячая бутэлечка", "detectedSourceLanguage": "en", "input": "Baby bottle"},
{"translatedText": "Нацыянальны парк", "detectedSourceLanguage": "en", "input": "National park"},
{"translatedText": "Круцяцца сэрцы", "detectedSourceLanguage": "en", "input": "Revolving hearts"},
{"translatedText": "Гібіскус", "detectedSourceLanguage": "en", "input": "Hibiscus"},
{"translatedText": "Парасон", "detectedSourceLanguage": "en", "input": "Umbrella"},
{"translatedText": "Парашут", "detectedSourceLanguage": "en", "input": "Parachute"},
{"translatedText": "Пакутаваны твар", "detectedSourceLanguage": "en", "input": "Anguished face"},
{"translatedText": "Круасан", "detectedSourceLanguage": "fr", "input": "Croissant"},
{"translatedText": "Самакат", "detectedSourceLanguage": "en", "input": "Kick scooter"},
{"translatedText": "Касцюм рыдлёўкі", "detectedSourceLanguage": "en", "input": "Spade suit"},
{"translatedText": "Службовы сабака", "detectedSourceLanguage": "en", "input": "Service dog"},
{"translatedText": "Сумочка", "detectedSourceLanguage": "en", "input": "Handbag"},
{"translatedText": "Венік", "detectedSourceLanguage": "en", "input": "Broom"},
{"translatedText": "Звязаныя сашчэпкі", "detectedSourceLanguage": "en", "input": "Linked paperclips"},
{"translatedText": "Джынсы", "detectedSourceLanguage": "en", "input": "Jeans"},
{"translatedText": "Краб", "detectedSourceLanguage": "en", "input": "Crab"},
{"translatedText": "Твар з паднятымі брывамі", "detectedSourceLanguage": "en", "input": "Face with raised eyebrow"},
{"translatedText": "Высокае напружанне", "detectedSourceLanguage": "en", "input": "High voltage"},
{"translatedText": "Кот", "detectedSourceLanguage": "en", "input": "Cat"},
{"translatedText": "Пяро", "detectedSourceLanguage": "en", "input": "Pen"},
{"translatedText": "Адкрытая кніга", "detectedSourceLanguage": "en", "input": "Open book"},
{"translatedText": "Вінаград", "detectedSourceLanguage": "en", "input": "Grapes"},
{"translatedText": "Звон", "detectedSourceLanguage": "en", "input": "Bell"},
{"translatedText": "Бурыта", "detectedSourceLanguage": "en", "input": "Burrito"},
{"translatedText": "Замак", "detectedSourceLanguage": "en", "input": "Castle"},
{"translatedText": "Слуп цырульніка", "detectedSourceLanguage": "en", "input": "Barber pole"},
{"translatedText": "Сустрэчны аўтобус", "detectedSourceLanguage": "en", "input": "Oncoming bus"},
{"translatedText": "Квітнець", "detectedSourceLanguage": "en", "input": "Blossom"},
{"translatedText": "Латок для выходных скрынь", "detectedSourceLanguage": "en", "input": "Outbox tray"},
{"translatedText": "Сэрца са стрэлкай", "detectedSourceLanguage": "en", "input": "Heart with arrow"},
{"translatedText": "Шалік", "detectedSourceLanguage": "en", "input": "Scarf"},
{"translatedText": "Бурундук", "detectedSourceLanguage": "en", "input": "Chipmunk"},
{"translatedText": "Сімвал гневу", "detectedSourceLanguage": "en", "input": "Anger symbol"},
{"translatedText": "Банкнота еўра", "detectedSourceLanguage": "en", "input": "Euro banknote"},
{"translatedText": "Адміністрацыйны будынак", "detectedSourceLanguage": "en", "input": "Office building"},
{"translatedText": "Трапічны напой", "detectedSourceLanguage": "en", "input": "Tropical drink"},
{"translatedText": "Футбольны мяч", "detectedSourceLanguage": "en", "input": "Soccer ball"},
{"translatedText": "Твар са слязамі радасці", "detectedSourceLanguage": "en", "input": "Face with tears of joy"},
{"translatedText": "Упакаваны падарунак", "detectedSourceLanguage": "en", "input": "Wrapped gift"},
{"translatedText": "Паголены лёд", "detectedSourceLanguage": "en", "input": "Shaved ice"},
{"translatedText": "Твар блазна", "detectedSourceLanguage": "en", "input": "Clown face"},
{"translatedText": "Бульба", "detectedSourceLanguage": "en", "input": "Potato"},
{"translatedText": "Хуткая дапамога", "detectedSourceLanguage": "en", "input": "Ambulance"},
{"translatedText": "Кальмары", "detectedSourceLanguage": "en", "input": "Squid"},
{"translatedText": "Крама", "detectedSourceLanguage": "en", "input": "Convenience store"},
{"translatedText": "Твар тыгра", "detectedSourceLanguage": "en", "input": "Tiger face"},
{"translatedText": "Ліхтарык", "detectedSourceLanguage": "en", "input": "Flashlight"},
{"translatedText": "Чорны кот", "detectedSourceLanguage": "en", "input": "Black cat"},
{"translatedText": "Воблака з маланкай", "detectedSourceLanguage": "en", "input": "Cloud with lightning"},
{"translatedText": "Твар з языком", "detectedSourceLanguage": "en", "input": "Face with tongue"},
{"translatedText": "Карова", "detectedSourceLanguage": "en", "input": "Cow"},
{"translatedText": "Дванаццатая гадзіна", "detectedSourceLanguage": "en", "input": "Twelve o’clock"},
{"translatedText": "Картатэка", "detectedSourceLanguage": "en", "input": "File cabinet"},
{"translatedText": "Чашка Петры", "detectedSourceLanguage": "en", "input": "Petri dish"},
{"translatedText": "Ровар", "detectedSourceLanguage": "en", "input": "Bicycle"},
{"translatedText": "Паштовы ражок", "detectedSourceLanguage": "en", "input": "Postal horn"},
{"translatedText": "Дзіцяня птушаня", "detectedSourceLanguage": "en", "input": "Baby chick"},
{"translatedText": "Гарадскі пейзаж у прыцемках", "detectedSourceLanguage": "en", "input": "Cityscape at dusk"},
{"translatedText": "Павялічальнае шкло, нахіленае ўправа", "detectedSourceLanguage": "en", "input": "Magnifying glass tilted right"},
{"translatedText": "пінг-понг", "detectedSourceLanguage": "en", "input": "Ping pong"},
{"translatedText": "Палягчэў твар", "detectedSourceLanguage": "en", "input": "Relieved face"},
{"translatedText": "Шпіталь", "detectedSourceLanguage": "en", "input": "Hospital"},
{"translatedText": "Трамвайны вагон", "detectedSourceLanguage": "en", "input": "Tram car"},
{"translatedText": "Куча калу", "detectedSourceLanguage": "en", "input": "Pile of poo"},
{"translatedText": "Джек-ліхтар", "detectedSourceLanguage": "el", "input": "Jack-o-lantern"},
{"translatedText": "Хуткасны цягнік", "detectedSourceLanguage": "en", "input": "High-speed train"},
{"translatedText": "Пража", "detectedSourceLanguage": "en", "input": "Yarn"},
{"translatedText": "Ліставая зялёная", "detectedSourceLanguage": "en", "input": "Leafy green"},
{"translatedText": "Каноэ", "detectedSourceLanguage": "en", "input": "Canoe"},
{"translatedText": "Адзін", "detectedSourceLanguage": "eu", "input": "Bat"},
{"translatedText": "Музычная клавіятура", "detectedSourceLanguage": "en", "input": "Musical keyboard"},
{"translatedText": "Кавун", "detectedSourceLanguage": "en", "input": "Watermelon"},
{"translatedText": "Тэрмометр", "detectedSourceLanguage": "en", "input": "Thermometer"},
{"translatedText": "Мыла", "detectedSourceLanguage": "en", "input": "Soap"},
{"translatedText": "Мегафон", "detectedSourceLanguage": "en", "input": "Megaphone"},
{"translatedText": "Кемпінг", "detectedSourceLanguage": "en", "input": "Camping"},
{"translatedText": "Матрасы", "detectedSourceLanguage": "en", "input": "Nesting dolls"},
{"translatedText": "Сабака", "detectedSourceLanguage": "en", "input": "Dog"},
{"translatedText": "Шахматная пешка", "detectedSourceLanguage": "en", "input": "Chess pawn"},
{"translatedText": "Іскрыстае сэрца", "detectedSourceLanguage": "en", "input": "Sparkling heart"},
{"translatedText": "Каршун", "detectedSourceLanguage": "en", "input": "Kite"},
{"translatedText": "Кабан", "detectedSourceLanguage": "en", "input": "Boar"},
{"translatedText": "Рысавы крекер", "detectedSourceLanguage": "en", "input": "Rice cracker"},
{"translatedText": "Чыгуначны вагон", "detectedSourceLanguage": "en", "input": "Railway car"},
{"translatedText": "Трусік", "detectedSourceLanguage": "en", "input": "Rabbit"},
{"translatedText": "кінапраектар", "detectedSourceLanguage": "nl", "input": "Film projector"},
{"translatedText": "Матарызаваная інвалідная каляска", "detectedSourceLanguage": "en", "input": "Motorized wheelchair"},
{"translatedText": "Глядзець", "detectedSourceLanguage": "en", "input": "Watch"},
{"translatedText": "Пікап", "detectedSourceLanguage": "en", "input": "Pickup truck"},
{"translatedText": "Робат", "detectedSourceLanguage": "en", "input": "Robot"},
{"translatedText": "Туман", "detectedSourceLanguage": "hu", "input": "Fog"},
{"translatedText": "Хакей на траве", "detectedSourceLanguage": "en", "input": "Field hockey"},
{"translatedText": "Адзінаццаць гадзін", "detectedSourceLanguage": "en", "input": "Eleven o’clock"},
{"translatedText": "Лабараторны халат", "detectedSourceLanguage": "en", "input": "Lab coat"},
{"translatedText": "Жаночая вопратка", "detectedSourceLanguage": "en", "input": "Woman’s clothes"},
{"translatedText": "Глобус з мерыдыянамі", "detectedSourceLanguage": "en", "input": "Globe with meridians"},
{"translatedText": "Назар абярэг", "detectedSourceLanguage": "hi", "input": "Nazar amulet"},
{"translatedText": "Арахіс", "detectedSourceLanguage": "en", "input": "Peanuts"},
{"translatedText": "Мабільны тэлефон", "detectedSourceLanguage": "en", "input": "Mobile phone"},
{"translatedText": "Авечка", "detectedSourceLanguage": "eo", "input": "Ewe"},
{"translatedText": "Сушы", "detectedSourceLanguage": "en", "input": "Sushi"},
{"translatedText": "Вярблюд", "detectedSourceLanguage": "en", "input": "Camel"},
{"translatedText": "Ззяючы твар з усмешлівымі вачыма", "detectedSourceLanguage": "en", "input": "Beaming face with smiling eyes"},
{"translatedText": "Твар закрыць рукой рот", "detectedSourceLanguage": "en", "input": "Face with hand over mouth"},
{"translatedText": "Турцыя", "detectedSourceLanguage": "en", "input": "Turkey"},
{"translatedText": "Чарапаха", "detectedSourceLanguage": "en", "input": "Turtle"},
{"translatedText": "Маторная лодка", "detectedSourceLanguage": "en", "input": "Motor boat"},
{"translatedText": "Гульнявой аўтамат", "detectedSourceLanguage": "en", "input": "Slot machine"},
{"translatedText": "Бомба", "detectedSourceLanguage": "en", "input": "Bomb"},
{"translatedText": "Слон", "detectedSourceLanguage": "en", "input": "Elephant"},
{"translatedText": "Мост ноччу", "detectedSourceLanguage": "en", "input": "Bridge at night"},
{"translatedText": "Ліхацца", "detectedSourceLanguage": "en", "input": "Dashing away"},
{"translatedText": "Цалуючы твар з зачыненымі вачыма", "detectedSourceLanguage": "en", "input": "Kissing face with closed eyes"},
{"translatedText": "Аловак", "detectedSourceLanguage": "en", "input": "Pencil"},
{"translatedText": "Зялёная кніга", "detectedSourceLanguage": "en", "input": "Green book"},
{"translatedText": "Страшны твар", "detectedSourceLanguage": "en", "input": "Fearful face"},
{"translatedText": "Сабачы твар", "detectedSourceLanguage": "en", "input": "Dog face"},
{"translatedText": "Шлем выратавальніка", "detectedSourceLanguage": "en", "input": "Rescue worker’s helmet"},
{"translatedText": "Свечка", "detectedSourceLanguage": "en", "input": "Candle"},
{"translatedText": "Сліны твар", "detectedSourceLanguage": "en", "input": "Drooling face"},
{"translatedText": "Галавакружэнне твар", "detectedSourceLanguage": "en", "input": "Dizzy face"},
{"translatedText": "Млечны Шлях", "detectedSourceLanguage": "en", "input": "Milky way"},
{"translatedText": "Карычневае сэрца", "detectedSourceLanguage": "en", "input": "Brown heart"},
{"translatedText": "Цыркавая палатка", "detectedSourceLanguage": "en", "input": "Circus tent"},
{"translatedText": "Сотня балаў", "detectedSourceLanguage": "en", "input": "Hundred points"},
{"translatedText": "Японскі замак", "detectedSourceLanguage": "en", "input": "Japanese castle"},
{"translatedText": "Звякаюць піўныя кружкі", "detectedSourceLanguage": "en", "input": "Clinking beer mugs"},
{"translatedText": "Кімано", "detectedSourceLanguage": "en", "input": "Kimono"},
{"translatedText": "Медаль за 2 месца", "detectedSourceLanguage": "en", "input": "2nd place medal"},
{"translatedText": "Гарачыя крыніцы", "detectedSourceLanguage": "en", "input": "Hot springs"},
{"translatedText": "Твар смакуе ежу", "detectedSourceLanguage": "en", "input": "Face savoring food"},
{"translatedText": "Пачырванелы твар", "detectedSourceLanguage": "en", "input": "Flushed face"},
{"translatedText": "Лакрос", "detectedSourceLanguage": "en", "input": "Lacrosse"},
{"translatedText": "Рыс кары", "detectedSourceLanguage": "en", "input": "Curry rice"},
{"translatedText": "Пустынны востраў", "detectedSourceLanguage": "en", "input": "Desert island"},
{"translatedText": "Ванна", "detectedSourceLanguage": "en", "input": "Bathtub"},
{"translatedText": "Ложак", "detectedSourceLanguage": "en", "input": "Bed"},
{"translatedText": "Басаножкі-стрынгі", "detectedSourceLanguage": "en", "input": "Thong sandal"},
{"translatedText": "06:00", "detectedSourceLanguage": "en", "input": "Six o’clock"},
{"translatedText": "Дзесяць трыццаць", "detectedSourceLanguage": "en", "input": "Ten-thirty"},
{"translatedText": "Нарастаючы месяц", "detectedSourceLanguage": "en", "input": "Waxing gibbous moon"},
{"translatedText": "Воблака", "detectedSourceLanguage": "en", "input": "Cloud"},
{"translatedText": "Твар поўнага месяца", "detectedSourceLanguage": "en", "input": "Full moon face"},
{"translatedText": "Кінакамера", "detectedSourceLanguage": "en", "input": "Movie camera"},
{"translatedText": "Уваходны канверт", "detectedSourceLanguage": "en", "input": "Incoming envelope"},
{"translatedText": "Ананас", "detectedSourceLanguage": "en", "input": "Pineapple"},
{"translatedText": "Гонкавая машына", "detectedSourceLanguage": "en", "input": "Racing car"},
{"translatedText": "Сонца за вялікім воблакам", "detectedSourceLanguage": "en", "input": "Sun behind large cloud"},
{"translatedText": "Спадарожнікавая антэна", "detectedSourceLanguage": "en", "input": "Satellite antenna"},
{"translatedText": "Мядзведзь", "detectedSourceLanguage": "en", "input": "Bear"},
{"translatedText": "Сэрцавы вокліч", "detectedSourceLanguage": "en", "input": "Heart exclamation"},
{"translatedText": "Пажарная машына", "detectedSourceLanguage": "en", "input": "Fire engine"},
{"translatedText": "Кубак з саломай", "detectedSourceLanguage": "en", "input": "Cup with straw"},
{"translatedText": "Закрыты парасон", "detectedSourceLanguage": "en", "input": "Closed umbrella"},
{"translatedText": "Шчыт", "detectedSourceLanguage": "en", "input": "Shield"},
{"translatedText": "Трамвай", "detectedSourceLanguage": "en", "input": "Tram"},
{"translatedText": "Цалуецца кот", "detectedSourceLanguage": "en", "input": "Kissing cat"},
{"translatedText": "Плюшавы мішка", "detectedSourceLanguage": "en", "input": "Teddy bear"},
{"translatedText": "Згорнутая газета", "detectedSourceLanguage": "en", "input": "Rolled-up newspaper"},
{"translatedText": "Гучна плача твар", "detectedSourceLanguage": "en", "input": "Loudly crying face"},
{"translatedText": "Скрынка для напояў", "detectedSourceLanguage": "en", "input": "Beverage box"},
{"translatedText": "Нарастаючы паўмесяц", "detectedSourceLanguage": "en", "input": "Waxing crescent moon"},
{"translatedText": "Халодны твар", "detectedSourceLanguage": "en", "input": "Cold face"},
{"translatedText": "Трактар", "detectedSourceLanguage": "en", "input": "Tractor"},
{"translatedText": "Клёцкі", "detectedSourceLanguage": "en", "input": "Dumpling"},
{"translatedText": "Восем гадзін", "detectedSourceLanguage": "en", "input": "Eight o’clock"},
{"translatedText": "Спіральная абалонка", "detectedSourceLanguage": "en", "input": "Spiral shell"},
{"translatedText": "Тарнада", "detectedSourceLanguage": "en", "input": "Tornado"},
{"translatedText": "Дзве гадзіны", "detectedSourceLanguage": "en", "input": "Two o’clock"},
{"translatedText": "Усмешлівы твар", "detectedSourceLanguage": "en", "input": "Smiling face"},
{"translatedText": "Прамая лінейка", "detectedSourceLanguage": "en", "input": "Straight ruler"},
{"translatedText": "кола агляду", "detectedSourceLanguage": "en", "input": "Ferris wheel"},
{"translatedText": "Сэрца са стужкай", "detectedSourceLanguage": "en", "input": "Heart with ribbon"},
{"translatedText": "Шкарпэткі", "detectedSourceLanguage": "en", "input": "Socks"}
]
